register_ex/__init__.py
register_ex/register.py
unit_testing_best_practice/__init__.py
unit_testing_best_practice/sample.py
mlops_labs_julls-0.1.0.dist-info/METADATA
mlops_labs_julls-0.1.0.dist-info/WHEEL
mlops_labs_julls-0.1.0.dist-info/top_level.txt
mlops_labs_julls-0.1.0.dist-info/RECORD
