Metadata-Version: 2.4
Name: mlops-labs-julls
Version: 0.1.0
Summary: MLOps labs project
Author: Julianlls
Project-URL: Homepage, https://github.com/Julianlls/MLOps_labs
Requires-Python: >=3.8
